amorprot/AmorProt.py
amorprot/__init__.py
amorprot-1.0.1.dist-info/METADATA
amorprot-1.0.1.dist-info/WHEEL
amorprot-1.0.1.dist-info/top_level.txt
amorprot-1.0.1.dist-info/RECORD
